{
  "id": "8e8f5f2c-8b2f-4f16-8ce4-3f7b8fba4d22",
  "name": "projet_backend local",
  "values": [
    {
      "key": "base_url",
      "value": "http://127.0.0.1:8000/api",
      "type": "default",
      "enabled": true
    },
    {
      "key": "token",
      "value": "",
      "type": "default",
      "enabled": true
    },
    {
      "key": "offre_id",
      "value": "1",
      "type": "default",
      "enabled": true
    },
    {
      "key": "profil_id",
      "value": "1",
      "type": "default",
      "enabled": true
    },
    {
      "key": "candidature_id",
      "value": "1",
      "type": "default",
      "enabled": true
    },
    {
      "key": "competence_id",
      "value": "1",
      "type": "default",
      "enabled": true
    }
  ],
  "_postman_variable_scope": "environment",
  "_postman_exported_at": "2026-04-19T00:00:00.000Z",
  "_postman_exported_using": "Copilot"
}